[
  {
    "emission": "382.2354842",
    "continent": " North America",
    "year": "1965",
    "peryearrang": "1"
  },
  {
    "emission": "401.2853728",
    "continent": " North America",
    "year": "1966",
    "peryearrang": "2"
  },
  {
    "emission": "417.8806938",
    "continent": " North America",
    "year": "1967",
    "peryearrang": "3"
  },
  {
    "emission": "445.919789",
    "continent": " North America",
    "year": "1968",
    "peryearrang": "4"
  },
  {
    "emission": "467.9359622",
    "continent": " North America",
    "year": "1969",
    "peryearrang": "5"
  },
  {
    "emission": "490.1749317",
    "continent": " North America",
    "year": "1970",
    "peryearrang": "6"
  },
  {
    "emission": "507.1687598",
    "continent": " North America",
    "year": "1971",
    "peryearrang": "7"
  },
  {
    "emission": "546.2313355",
    "continent": " North America",
    "year": "1972",
    "peryearrang": "8"
  },
  {
    "emission": "580.5134444",
    "continent": " North America",
    "year": "1973",
    "peryearrang": "9"
  },
  {
    "emission": "563.1667193",
    "continent": " North America",
    "year": "1974",
    "peryearrang": "10"
  },
  {
    "emission": "551.9461255",
    "continent": " North America",
    "year": "1975",
    "peryearrang": "11"
  },
  {
    "emission": "591.7810532",
    "continent": " North America",
    "year": "1976",
    "peryearrang": "12"
  },
  {
    "emission": "622.3642495",
    "continent": " North America",
    "year": "1977",
    "peryearrang": "13"
  },
  {
    "emission": "639.1458935",
    "continent": " North America",
    "year": "1978",
    "peryearrang": "14"
  },
  {
    "emission": "630.1494845",
    "continent": " North America",
    "year": "1979",
    "peryearrang": "15"
  },
  {
    "emission": "589.4573431",
    "continent": " North America",
    "year": "1980",
    "peryearrang": "16"
  },
  {
    "emission": "554.7498222",
    "continent": " North America",
    "year": "1981",
    "peryearrang": "17"
  },
  {
    "emission": "525.2851724",
    "continent": " North America",
    "year": "1982",
    "peryearrang": "18"
  },
  {
    "emission": "518.8445076",
    "continent": " North America",
    "year": "1983",
    "peryearrang": "19"
  },
  {
    "emission": "534.9481645",
    "continent": " North America",
    "year": "1984",
    "peryearrang": "20"
  },
  {
    "emission": "534.6315613",
    "continent": " North America",
    "year": "1985",
    "peryearrang": "21"
  },
  {
    "emission": "557.7358965",
    "continent": " North America",
    "year": "1986",
    "peryearrang": "22"
  },
  {
    "emission": "570.8594125",
    "continent": " North America",
    "year": "1987",
    "peryearrang": "23"
  },
  {
    "emission": "593.5569942",
    "continent": " North America",
    "year": "1988",
    "peryearrang": "24"
  },
  {
    "emission": "598.0802111",
    "continent": " North America",
    "year": "1989",
    "peryearrang": "25"
  },
  {
    "emission": "585.6882822",
    "continent": " North America",
    "year": "1990",
    "peryearrang": "26"
  },
  {
    "emission": "573.7608622",
    "continent": " North America",
    "year": "1991",
    "peryearrang": "27"
  },
  {
    "emission": "585.9123748",
    "continent": " North America",
    "year": "1992",
    "peryearrang": "28"
  },
  {
    "emission": "590.0864037",
    "continent": " North America",
    "year": "1993",
    "peryearrang": "29"
  },
  {
    "emission": "607.7142365",
    "continent": " North America",
    "year": "1994",
    "peryearrang": "30"
  },
  {
    "emission": "604.6746971",
    "continent": " North America",
    "year": "1995",
    "peryearrang": "31"
  },
  {
    "emission": "625.7107649",
    "continent": " North America",
    "year": "1996",
    "peryearrang": "32"
  },
  {
    "emission": "635.8650331",
    "continent": " North America",
    "year": "1997",
    "peryearrang": "33"
  },
  {
    "emission": "649.3559467",
    "continent": " North America",
    "year": "1998",
    "peryearrang": "34"
  },
  {
    "emission": "664.8504954",
    "continent": " North America",
    "year": "1999",
    "peryearrang": "35"
  },
  {
    "emission": "672.0779094",
    "continent": " North America",
    "year": "2000",
    "peryearrang": "36"
  },
  {
    "emission": "672.6122175",
    "continent": " North America",
    "year": "2001",
    "peryearrang": "37"
  },
  {
    "emission": "672.31646",
    "continent": " North America",
    "year": "2002",
    "peryearrang": "38"
  },
  {
    "emission": "685.0250251",
    "continent": " North America",
    "year": "2003",
    "peryearrang": "39"
  },
  {
    "emission": "711.7901474",
    "continent": " North America",
    "year": "2004",
    "peryearrang": "40"
  },
  {
    "emission": "712.3250104",
    "continent": " North America",
    "year": "2005",
    "peryearrang": "41"
  },
  {
    "emission": "704.3574141",
    "continent": " North America",
    "year": "2006",
    "peryearrang": "42"
  },
  {
    "emission": "704.4159843",
    "continent": " North America",
    "year": "2007",
    "peryearrang": "43"
  },
  {
    "emission": "663.2690548",
    "continent": " North America",
    "year": "2008",
    "peryearrang": "44"
  },
  {
    "emission": "630.2257973",
    "continent": " North America",
    "year": "2009",
    "peryearrang": "45"
  },
  {
    "emission": "640.4927775",
    "continent": " North America",
    "year": "2010",
    "peryearrang": "46"
  },
  {
    "emission": "630.8033403",
    "continent": " North America",
    "year": "2011",
    "peryearrang": "47"
  },
  {
    "emission": "621.2139835",
    "continent": " North America",
    "year": "2012",
    "peryearrang": "48"
  },
  {
    "emission": "626.860301",
    "continent": " North America",
    "year": "2013",
    "peryearrang": "49"
  },
  {
    "emission": "627.1732287",
    "continent": " North America",
    "year": "2014",
    "peryearrang": "50"
  },
  {
    "emission": "637.0876927",
    "continent": " North America",
    "year": "2015",
    "peryearrang": "51"
  },
  {
    "emission": "640.4650095",
    "continent": " North America",
    "year": "2016",
    "peryearrang": "52"
  },
  {
    "emission": "642.5871266",
    "continent": " North America",
    "year": "2017",
    "peryearrang": "53"
  },
  {
    "emission": "655.6839763",
    "continent": " North America",
    "year": "2018",
    "peryearrang": "54"
  },
  {
    "emission": "650.6327619",
    "continent": " North America",
    "year": "2019",
    "peryearrang": "55"
  },
  {
    "emission": "565.440136",
    "continent": " North America",
    "year": "2020",
    "peryearrang": "56"
  },
  {
    "emission": "608.3612728",
    "continent": " North America",
    "year": "2021",
    "peryearrang": "57"
  },
  {
    "emission": "54.46902247",
    "continent": "S. & Cent. America",
    "year": "1965.2",
    "peryearrang": "58"
  },
  {
    "emission": "57.26704649",
    "continent": "S. & Cent. America",
    "year": "1966.2",
    "peryearrang": "59"
  },
  {
    "emission": "58.89016812",
    "continent": "S. & Cent. America",
    "year": "1967.2",
    "peryearrang": "60"
  },
  {
    "emission": "62.87841751",
    "continent": "S. & Cent. America",
    "year": "1968.2",
    "peryearrang": "61"
  },
  {
    "emission": "65.22360146",
    "continent": "S. & Cent. America",
    "year": "1969.2",
    "peryearrang": "62"
  },
  {
    "emission": "68.63311489",
    "continent": "S. & Cent. America",
    "year": "1970.2",
    "peryearrang": "63"
  },
  {
    "emission": "72.17745549",
    "continent": "S. & Cent. America",
    "year": "1971.2",
    "peryearrang": "64"
  },
  {
    "emission": "77.83932354",
    "continent": "S. & Cent. America",
    "year": "1972.2",
    "peryearrang": "65"
  },
  {
    "emission": "85.19102405",
    "continent": "S. & Cent. America",
    "year": "1973.2",
    "peryearrang": "66"
  },
  {
    "emission": "88.08069013",
    "continent": "S. & Cent. America",
    "year": "1974.2",
    "peryearrang": "67"
  },
  {
    "emission": "87.87639362",
    "continent": "S. & Cent. America",
    "year": "1975.2",
    "peryearrang": "68"
  },
  {
    "emission": "91.79232829",
    "continent": "S. & Cent. America",
    "year": "1976.2",
    "peryearrang": "69"
  },
  {
    "emission": "95.81702654",
    "continent": "S. & Cent. America",
    "year": "1977.2",
    "peryearrang": "70"
  },
  {
    "emission": "99.36192212",
    "continent": "S. & Cent. America",
    "year": "1978.2",
    "peryearrang": "71"
  },
  {
    "emission": "103.8855964",
    "continent": "S. & Cent. America",
    "year": "1979.2",
    "peryearrang": "72"
  },
  {
    "emission": "105.9641305",
    "continent": "S. & Cent. America",
    "year": "1980.2",
    "peryearrang": "73"
  },
  {
    "emission": "104.7282232",
    "continent": "S. & Cent. America",
    "year": "1981.2",
    "peryearrang": "74"
  },
  {
    "emission": "100.9930438",
    "continent": "S. & Cent. America",
    "year": "1982.2",
    "peryearrang": "75"
  },
  {
    "emission": "97.22222154",
    "continent": "S. & Cent. America",
    "year": "1983.2",
    "peryearrang": "76"
  },
  {
    "emission": "97.1592627",
    "continent": "S. & Cent. America",
    "year": "1984.2",
    "peryearrang": "77"
  },
  {
    "emission": "96.33466304",
    "continent": "S. & Cent. America",
    "year": "1985.2",
    "peryearrang": "78"
  },
  {
    "emission": "100.9037889",
    "continent": "S. & Cent. America",
    "year": "1986.2",
    "peryearrang": "79"
  },
  {
    "emission": "103.4101237",
    "continent": "S. & Cent. America",
    "year": "1987.2",
    "peryearrang": "80"
  },
  {
    "emission": "105.901597",
    "continent": "S. & Cent. America",
    "year": "1988.2",
    "peryearrang": "81"
  },
  {
    "emission": "105.96565",
    "continent": "S. & Cent. America",
    "year": "1989.2",
    "peryearrang": "82"
  },
  {
    "emission": "104.9368967",
    "continent": "S. & Cent. America",
    "year": "1990.2",
    "peryearrang": "83"
  },
  {
    "emission": "105.9166661",
    "continent": "S. & Cent. America",
    "year": "1991.2",
    "peryearrang": "84"
  },
  {
    "emission": "113.5274692",
    "continent": "S. & Cent. America",
    "year": "1992.2",
    "peryearrang": "85"
  },
  {
    "emission": "114.7957081",
    "continent": "S. & Cent. America",
    "year": "1993.2",
    "peryearrang": "86"
  },
  {
    "emission": "122.9147977",
    "continent": "S. & Cent. America",
    "year": "1994.2",
    "peryearrang": "87"
  },
  {
    "emission": "126.8295484",
    "continent": "S. & Cent. America",
    "year": "1995.2",
    "peryearrang": "88"
  },
  {
    "emission": "129.0529909",
    "continent": "S. & Cent. America",
    "year": "1996.2",
    "peryearrang": "89"
  },
  {
    "emission": "137.3333414",
    "continent": "S. & Cent. America",
    "year": "1997.2",
    "peryearrang": "90"
  },
  {
    "emission": "143.2119291",
    "continent": "S. & Cent. America",
    "year": "1998.2",
    "peryearrang": "91"
  },
  {
    "emission": "145.2623923",
    "continent": "S. & Cent. America",
    "year": "1999.2",
    "peryearrang": "92"
  },
  {
    "emission": "145.3481415",
    "continent": "S. & Cent. America",
    "year": "2000.2",
    "peryearrang": "93"
  },
  {
    "emission": "146.6224229",
    "continent": "S. & Cent. America",
    "year": "2001.2",
    "peryearrang": "94"
  },
  {
    "emission": "146.7394197",
    "continent": "S. & Cent. America",
    "year": "2002.2",
    "peryearrang": "95"
  },
  {
    "emission": "144.3718715",
    "continent": "S. & Cent. America",
    "year": "2003.2",
    "peryearrang": "96"
  },
  {
    "emission": "149.1270633",
    "continent": "S. & Cent. America",
    "year": "2004.2",
    "peryearrang": "97"
  },
  {
    "emission": "152.7832563",
    "continent": "S. & Cent. America",
    "year": "2005.2",
    "peryearrang": "98"
  },
  {
    "emission": "155.7556139",
    "continent": "S. & Cent. America",
    "year": "2006.2",
    "peryearrang": "99"
  },
  {
    "emission": "164.3013717",
    "continent": "S. & Cent. America",
    "year": "2007.2",
    "peryearrang": "100"
  },
  {
    "emission": "168.3607468",
    "continent": "S. & Cent. America",
    "year": "2008.2",
    "peryearrang": "101"
  },
  {
    "emission": "165.9200231",
    "continent": "S. & Cent. America",
    "year": "2009.2",
    "peryearrang": "102"
  },
  {
    "emission": "174.6392362",
    "continent": "S. & Cent. America",
    "year": "2010.2",
    "peryearrang": "103"
  },
  {
    "emission": "181.3205537",
    "continent": "S. & Cent. America",
    "year": "2011.2",
    "peryearrang": "104"
  },
  {
    "emission": "187.0319429",
    "continent": "S. & Cent. America",
    "year": "2012.2",
    "peryearrang": "105"
  },
  {
    "emission": "193.7224521",
    "continent": "S. & Cent. America",
    "year": "2013.2",
    "peryearrang": "106"
  },
  {
    "emission": "193.6025182",
    "continent": "S. & Cent. America",
    "year": "2014.2",
    "peryearrang": "107"
  },
  {
    "emission": "187.936903",
    "continent": "S. & Cent. America",
    "year": "2015.2",
    "peryearrang": "108"
  },
  {
    "emission": "180.6141673",
    "continent": "S. & Cent. America",
    "year": "2016.2",
    "peryearrang": "109"
  },
  {
    "emission": "178.8816629",
    "continent": "S. & Cent. America",
    "year": "2017.2",
    "peryearrang": "110"
  },
  {
    "emission": "173.1252524",
    "continent": "S. & Cent. America",
    "year": "2018.2",
    "peryearrang": "111"
  },
  {
    "emission": "171.4527275",
    "continent": "S. & Cent. America",
    "year": "2019.2",
    "peryearrang": "112"
  },
  {
    "emission": "150.8901681",
    "continent": "S. & Cent. America",
    "year": "2020.2",
    "peryearrang": "113"
  },
  {
    "emission": "165.6789376",
    "continent": "S. & Cent. America",
    "year": "2021.2",
    "peryearrang": "114"
  },
  {
    "emission": "268.1637972",
    "continent": "Europe",
    "year": "1965.3",
    "peryearrang": "115"
  },
  {
    "emission": "294.2103969",
    "continent": "Europe",
    "year": "1966.3",
    "peryearrang": "116"
  },
  {
    "emission": "319.0554635",
    "continent": "Europe",
    "year": "1967.3",
    "peryearrang": "117"
  },
  {
    "emission": "350.8710738",
    "continent": "Europe",
    "year": "1968.3",
    "peryearrang": "118"
  },
  {
    "emission": "390.744432",
    "continent": "Europe",
    "year": "1969.3",
    "peryearrang": "119"
  },
  {
    "emission": "433.1443133",
    "continent": "Europe",
    "year": "1970.3",
    "peryearrang": "120"
  },
  {
    "emission": "454.1374035",
    "continent": "Europe",
    "year": "1971.3",
    "peryearrang": "121"
  },
  {
    "emission": "485.9149053",
    "continent": "Europe",
    "year": "1972.3",
    "peryearrang": "122"
  },
  {
    "emission": "520.7277072",
    "continent": "Europe",
    "year": "1973.3",
    "peryearrang": "123"
  },
  {
    "emission": "490.1962931",
    "continent": "Europe",
    "year": "1974.3",
    "peryearrang": "124"
  },
  {
    "emission": "472.5876964",
    "continent": "Europe",
    "year": "1975.3",
    "peryearrang": "125"
  },
  {
    "emission": "504.7258",
    "continent": "Europe",
    "year": "1976.3",
    "peryearrang": "126"
  },
  {
    "emission": "500.2141574",
    "continent": "Europe",
    "year": "1977.3",
    "peryearrang": "127"
  },
  {
    "emission": "523.4807246",
    "continent": "Europe",
    "year": "1978.3",
    "peryearrang": "128"
  },
  {
    "emission": "535.4266554",
    "continent": "Europe",
    "year": "1979.3",
    "peryearrang": "129"
  },
  {
    "emission": "499.0799541",
    "continent": "Europe",
    "year": "1980.3",
    "peryearrang": "130"
  },
  {
    "emission": "464.4758308",
    "continent": "Europe",
    "year": "1981.3",
    "peryearrang": "131"
  },
  {
    "emission": "441.3372204",
    "continent": "Europe",
    "year": "1982.3",
    "peryearrang": "132"
  },
  {
    "emission": "429.1363636",
    "continent": "Europe",
    "year": "1983.3",
    "peryearrang": "133"
  },
  {
    "emission": "431.059904",
    "continent": "Europe",
    "year": "1984.3",
    "peryearrang": "134"
  },
  {
    "emission": "482.3865421",
    "continent": "Europe",
    "year": "1985.3",
    "peryearrang": "135"
  },
  {
    "emission": "497.3657146",
    "continent": "Europe",
    "year": "1986.3",
    "peryearrang": "136"
  },
  {
    "emission": "499.1728984",
    "continent": "Europe",
    "year": "1987.3",
    "peryearrang": "137"
  },
  {
    "emission": "501.2875334",
    "continent": "Europe",
    "year": "1988.3",
    "peryearrang": "138"
  },
  {
    "emission": "499.2914886",
    "continent": "Europe",
    "year": "1989.3",
    "peryearrang": "139"
  },
  {
    "emission": "509.5061975",
    "continent": "Europe",
    "year": "1990.3",
    "peryearrang": "140"
  },
  {
    "emission": "504.8948527",
    "continent": "Europe",
    "year": "1991.3",
    "peryearrang": "141"
  },
  {
    "emission": "491.5543755",
    "continent": "Europe",
    "year": "1992.3",
    "peryearrang": "142"
  },
  {
    "emission": "480.0756423",
    "continent": "Europe",
    "year": "1993.3",
    "peryearrang": "143"
  },
  {
    "emission": "477.6690967",
    "continent": "Europe",
    "year": "1994.3",
    "peryearrang": "144"
  },
  {
    "emission": "486.9085615",
    "continent": "Europe",
    "year": "1995.3",
    "peryearrang": "145"
  },
  {
    "emission": "491.9448872",
    "continent": "Europe",
    "year": "1996.3",
    "peryearrang": "146"
  },
  {
    "emission": "496.0267342",
    "continent": "Europe",
    "year": "1997.3",
    "peryearrang": "147"
  },
  {
    "emission": "506.0722932",
    "continent": "Europe",
    "year": "1998.3",
    "peryearrang": "148"
  },
  {
    "emission": "498.3479644",
    "continent": "Europe",
    "year": "1999.3",
    "peryearrang": "149"
  },
  {
    "emission": "491.7124667",
    "continent": "Europe",
    "year": "2000.3",
    "peryearrang": "150"
  },
  {
    "emission": "498.5495949",
    "continent": "Europe",
    "year": "2001.3",
    "peryearrang": "151"
  },
  {
    "emission": "497.0393256",
    "continent": "Europe",
    "year": "2002.3",
    "peryearrang": "152"
  },
  {
    "emission": "499.9991646",
    "continent": "Europe",
    "year": "2003.3",
    "peryearrang": "153"
  },
  {
    "emission": "504.9199686",
    "continent": "Europe",
    "year": "2004.3",
    "peryearrang": "154"
  },
  {
    "emission": "508.5649672",
    "continent": "Europe",
    "year": "2005.3",
    "peryearrang": "155"
  },
  {
    "emission": "510.1210946",
    "continent": "Europe",
    "year": "2006.3",
    "peryearrang": "156"
  },
  {
    "emission": "499.6415899",
    "continent": "Europe",
    "year": "2007.3",
    "peryearrang": "157"
  },
  {
    "emission": "494.4367202",
    "continent": "Europe",
    "year": "2008.3",
    "peryearrang": "158"
  },
  {
    "emission": "469.4671919",
    "continent": "Europe",
    "year": "2009.3",
    "peryearrang": "159"
  },
  {
    "emission": "463.8612561",
    "continent": "Europe",
    "year": "2010.3",
    "peryearrang": "160"
  },
  {
    "emission": "451.457065",
    "continent": "Europe",
    "year": "2011.3",
    "peryearrang": "161"
  },
  {
    "emission": "436.0563259",
    "continent": "Europe",
    "year": "2012.3",
    "peryearrang": "162"
  },
  {
    "emission": "427.5266002",
    "continent": "Europe",
    "year": "2013.3",
    "peryearrang": "163"
  },
  {
    "emission": "418.913915",
    "continent": "Europe",
    "year": "2014.3",
    "peryearrang": "164"
  },
  {
    "emission": "430.0357011",
    "continent": "Europe",
    "year": "2015.3",
    "peryearrang": "165"
  },
  {
    "emission": "440.366759",
    "continent": "Europe",
    "year": "2016.3",
    "peryearrang": "166"
  },
  {
    "emission": "447.8294661",
    "continent": "Europe",
    "year": "2017.3",
    "peryearrang": "167"
  },
  {
    "emission": "446.7743776",
    "continent": "Europe",
    "year": "2018.3",
    "peryearrang": "168"
  },
  {
    "emission": "444.6008129",
    "continent": "Europe",
    "year": "2019.3",
    "peryearrang": "169"
  },
  {
    "emission": "385.8488056",
    "continent": "Europe",
    "year": "2020.3",
    "peryearrang": "170"
  },
  {
    "emission": "404.8669683",
    "continent": "Europe",
    "year": "2021.3",
    "peryearrang": "171"
  },
  {
    "emission": "106.8928654",
    "continent": "CIS",
    "year": "1965.4",
    "peryearrang": "172"
  },
  {
    "emission": "114.4694579",
    "continent": "CIS",
    "year": "1966.4",
    "peryearrang": "173"
  },
  {
    "emission": "124.7179536",
    "continent": "CIS",
    "year": "1967.4",
    "peryearrang": "174"
  },
  {
    "emission": "132.9359528",
    "continent": "CIS",
    "year": "1968.4",
    "peryearrang": "175"
  },
  {
    "emission": "141.3480216",
    "continent": "CIS",
    "year": "1969.4",
    "peryearrang": "176"
  },
  {
    "emission": "155.6383645",
    "continent": "CIS",
    "year": "1970.4",
    "peryearrang": "177"
  },
  {
    "emission": "165.0419648",
    "continent": "CIS",
    "year": "1971.4",
    "peryearrang": "178"
  },
  {
    "emission": "179.0127916",
    "continent": "CIS",
    "year": "1972.4",
    "peryearrang": "179"
  },
  {
    "emission": "192.4591353",
    "continent": "CIS",
    "year": "1973.4",
    "peryearrang": "180"
  },
  {
    "emission": "211.5073076",
    "continent": "CIS",
    "year": "1974.4",
    "peryearrang": "181"
  },
  {
    "emission": "221.4913101",
    "continent": "CIS",
    "year": "1975.4",
    "peryearrang": "182"
  },
  {
    "emission": "227.6299687",
    "continent": "CIS",
    "year": "1976.4",
    "peryearrang": "183"
  },
  {
    "emission": "236.3187233",
    "continent": "CIS",
    "year": "1977.4",
    "peryearrang": "184"
  },
  {
    "emission": "250.7072052",
    "continent": "CIS",
    "year": "1978.4",
    "peryearrang": "185"
  },
  {
    "emission": "255.2178794",
    "continent": "CIS",
    "year": "1979.4",
    "peryearrang": "186"
  },
  {
    "emission": "267.6486825",
    "continent": "CIS",
    "year": "1980.4",
    "peryearrang": "187"
  },
  {
    "emission": "270.0824445",
    "continent": "CIS",
    "year": "1981.4",
    "peryearrang": "188"
  },
  {
    "emission": "268.2009426",
    "continent": "CIS",
    "year": "1982.4",
    "peryearrang": "189"
  },
  {
    "emission": "264.3634179",
    "continent": "CIS",
    "year": "1983.4",
    "peryearrang": "190"
  },
  {
    "emission": "264.4733345",
    "continent": "CIS",
    "year": "1984.4",
    "peryearrang": "191"
  },
  {
    "emission": "209.9259686",
    "continent": "CIS",
    "year": "1985.4",
    "peryearrang": "192"
  },
  {
    "emission": "212.7115624",
    "continent": "CIS",
    "year": "1986.4",
    "peryearrang": "193"
  },
  {
    "emission": "213.2733756",
    "continent": "CIS",
    "year": "1987.4",
    "peryearrang": "194"
  },
  {
    "emission": "212.0171931",
    "continent": "CIS",
    "year": "1988.4",
    "peryearrang": "195"
  },
  {
    "emission": "213.6718234",
    "continent": "CIS",
    "year": "1989.4",
    "peryearrang": "196"
  },
  {
    "emission": "214.7865971",
    "continent": "CIS",
    "year": "1990.4",
    "peryearrang": "197"
  },
  {
    "emission": "208.1757223",
    "continent": "CIS",
    "year": "1991.4",
    "peryearrang": "198"
  },
  {
    "emission": "193.3220503",
    "continent": "CIS",
    "year": "1992.4",
    "peryearrang": "199"
  },
  {
    "emission": "159.8294074",
    "continent": "CIS",
    "year": "1993.4",
    "peryearrang": "200"
  },
  {
    "emission": "138.1406505",
    "continent": "CIS",
    "year": "1994.4",
    "peryearrang": "201"
  },
  {
    "emission": "121.4534234",
    "continent": "CIS",
    "year": "1995.4",
    "peryearrang": "202"
  },
  {
    "emission": "106.505263",
    "continent": "CIS",
    "year": "1996.4",
    "peryearrang": "203"
  },
  {
    "emission": "104.9400431",
    "continent": "CIS",
    "year": "1997.4",
    "peryearrang": "204"
  },
  {
    "emission": "100.7470682",
    "continent": "CIS",
    "year": "1998.4",
    "peryearrang": "205"
  },
  {
    "emission": "101.0486061",
    "continent": "CIS",
    "year": "1999.4",
    "peryearrang": "206"
  },
  {
    "emission": "100.0705747",
    "continent": "CIS",
    "year": "2000.4",
    "peryearrang": "207"
  },
  {
    "emission": "100.7954522",
    "continent": "CIS",
    "year": "2001.4",
    "peryearrang": "208"
  },
  {
    "emission": "98.12556187",
    "continent": "CIS",
    "year": "2002.4",
    "peryearrang": "209"
  },
  {
    "emission": "102.2465661",
    "continent": "CIS",
    "year": "2003.4",
    "peryearrang": "210"
  },
  {
    "emission": "101.2433081",
    "continent": "CIS",
    "year": "2004.4",
    "peryearrang": "211"
  },
  {
    "emission": "101.1520002",
    "continent": "CIS",
    "year": "2005.4",
    "peryearrang": "212"
  },
  {
    "emission": "106.5652065",
    "continent": "CIS",
    "year": "2006.4",
    "peryearrang": "213"
  },
  {
    "emission": "106.3955127",
    "continent": "CIS",
    "year": "2007.4",
    "peryearrang": "214"
  },
  {
    "emission": "108.1687051",
    "continent": "CIS",
    "year": "2008.4",
    "peryearrang": "215"
  },
  {
    "emission": "103.3958547",
    "continent": "CIS",
    "year": "2009.4",
    "peryearrang": "216"
  },
  {
    "emission": "106.2158336",
    "continent": "CIS",
    "year": "2010.4",
    "peryearrang": "217"
  },
  {
    "emission": "115.6449533",
    "continent": "CIS",
    "year": "2011.4",
    "peryearrang": "218"
  },
  {
    "emission": "118.9273859",
    "continent": "CIS",
    "year": "2012.4",
    "peryearrang": "219"
  },
  {
    "emission": "116.8464701",
    "continent": "CIS",
    "year": "2013.4",
    "peryearrang": "220"
  },
  {
    "emission": "121.6270546",
    "continent": "CIS",
    "year": "2014.4",
    "peryearrang": "221"
  },
  {
    "emission": "116.4222141",
    "continent": "CIS",
    "year": "2015.4",
    "peryearrang": "222"
  },
  {
    "emission": "119.758827",
    "continent": "CIS",
    "year": "2016.4",
    "peryearrang": "223"
  },
  {
    "emission": "119.3920332",
    "continent": "CIS",
    "year": "2017.4",
    "peryearrang": "224"
  },
  {
    "emission": "122.7024863",
    "continent": "CIS",
    "year": "2018.4",
    "peryearrang": "225"
  },
  {
    "emission": "124.8212516",
    "continent": "CIS",
    "year": "2019.4",
    "peryearrang": "226"
  },
  {
    "emission": "116.8985661",
    "continent": "CIS",
    "year": "2020.4",
    "peryearrang": "227"
  },
  {
    "emission": "123.1344083",
    "continent": "CIS",
    "year": "2021.4",
    "peryearrang": "228"
  },
  {
    "emission": "26.53303433",
    "continent": "Middle East",
    "year": "1965.5",
    "peryearrang": "229"
  },
  {
    "emission": "27.19607119",
    "continent": "Middle East",
    "year": "1966.5",
    "peryearrang": "230"
  },
  {
    "emission": "28.37795263",
    "continent": "Middle East",
    "year": "1967.5",
    "peryearrang": "231"
  },
  {
    "emission": "29.22803894",
    "continent": "Middle East",
    "year": "1968.5",
    "peryearrang": "232"
  },
  {
    "emission": "30.39737264",
    "continent": "Middle East",
    "year": "1969.5",
    "peryearrang": "233"
  },
  {
    "emission": "32.1785815",
    "continent": "Middle East",
    "year": "1970.5",
    "peryearrang": "234"
  },
  {
    "emission": "34.47850567",
    "continent": "Middle East",
    "year": "1971.5",
    "peryearrang": "235"
  },
  {
    "emission": "36.63727316",
    "continent": "Middle East",
    "year": "1972.5",
    "peryearrang": "236"
  },
  {
    "emission": "39.71614473",
    "continent": "Middle East",
    "year": "1973.5",
    "peryearrang": "237"
  },
  {
    "emission": "42.171624",
    "continent": "Middle East",
    "year": "1974.5",
    "peryearrang": "238"
  },
  {
    "emission": "40.22751176",
    "continent": "Middle East",
    "year": "1975.5",
    "peryearrang": "239"
  },
  {
    "emission": "45.91459255",
    "continent": "Middle East",
    "year": "1976.5",
    "peryearrang": "240"
  },
  {
    "emission": "52.10174623",
    "continent": "Middle East",
    "year": "1977.5",
    "peryearrang": "241"
  },
  {
    "emission": "54.55696345",
    "continent": "Middle East",
    "year": "1978.5",
    "peryearrang": "242"
  },
  {
    "emission": "61.6668168",
    "continent": "Middle East",
    "year": "1979.5",
    "peryearrang": "243"
  },
  {
    "emission": "59.01254321",
    "continent": "Middle East",
    "year": "1980.5",
    "peryearrang": "244"
  },
  {
    "emission": "64.58153505",
    "continent": "Middle East",
    "year": "1981.5",
    "peryearrang": "245"
  },
  {
    "emission": "70.80379594",
    "continent": "Middle East",
    "year": "1982.5",
    "peryearrang": "246"
  },
  {
    "emission": "79.10048745",
    "continent": "Middle East",
    "year": "1983.5",
    "peryearrang": "247"
  },
  {
    "emission": "86.55185883",
    "continent": "Middle East",
    "year": "1984.5",
    "peryearrang": "248"
  },
  {
    "emission": "90.90802636",
    "continent": "Middle East",
    "year": "1985.5",
    "peryearrang": "249"
  },
  {
    "emission": "90.27555601",
    "continent": "Middle East",
    "year": "1986.5",
    "peryearrang": "250"
  },
  {
    "emission": "94.89323522",
    "continent": "Middle East",
    "year": "1987.5",
    "peryearrang": "251"
  },
  {
    "emission": "98.3679452",
    "continent": "Middle East",
    "year": "1988.5",
    "peryearrang": "252"
  },
  {
    "emission": "100.8037408",
    "continent": "Middle East",
    "year": "1989.5",
    "peryearrang": "253"
  },
  {
    "emission": "104.0942231",
    "continent": "Middle East",
    "year": "1990.5",
    "peryearrang": "254"
  },
  {
    "emission": "107.837108",
    "continent": "Middle East",
    "year": "1991.5",
    "peryearrang": "255"
  },
  {
    "emission": "114.7626011",
    "continent": "Middle East",
    "year": "1992.5",
    "peryearrang": "256"
  },
  {
    "emission": "122.9265098",
    "continent": "Middle East",
    "year": "1993.5",
    "peryearrang": "257"
  },
  {
    "emission": "135.0512444",
    "continent": "Middle East",
    "year": "1994.5",
    "peryearrang": "258"
  },
  {
    "emission": "134.2260359",
    "continent": "Middle East",
    "year": "1995.5",
    "peryearrang": "259"
  },
  {
    "emission": "137.045734",
    "continent": "Middle East",
    "year": "1996.5",
    "peryearrang": "260"
  },
  {
    "emission": "144.1827244",
    "continent": "Middle East",
    "year": "1997.5",
    "peryearrang": "261"
  },
  {
    "emission": "143.1286231",
    "continent": "Middle East",
    "year": "1998.5",
    "peryearrang": "262"
  },
  {
    "emission": "142.6033036",
    "continent": "Middle East",
    "year": "1999.5",
    "peryearrang": "263"
  },
  {
    "emission": "149.8051033",
    "continent": "Middle East",
    "year": "2000.5",
    "peryearrang": "264"
  },
  {
    "emission": "155.9537397",
    "continent": "Middle East",
    "year": "2001.5",
    "peryearrang": "265"
  },
  {
    "emission": "159.2344635",
    "continent": "Middle East",
    "year": "2002.5",
    "peryearrang": "266"
  },
  {
    "emission": "164.56269",
    "continent": "Middle East",
    "year": "2003.5",
    "peryearrang": "267"
  },
  {
    "emission": "175.7428603",
    "continent": "Middle East",
    "year": "2004.5",
    "peryearrang": "268"
  },
  {
    "emission": "182.3512551",
    "continent": "Middle East",
    "year": "2005.5",
    "peryearrang": "269"
  },
  {
    "emission": "189.8640509",
    "continent": "Middle East",
    "year": "2006.5",
    "peryearrang": "270"
  },
  {
    "emission": "194.7600531",
    "continent": "Middle East",
    "year": "2007.5",
    "peryearrang": "271"
  },
  {
    "emission": "208.9744263",
    "continent": "Middle East",
    "year": "2008.5",
    "peryearrang": "272"
  },
  {
    "emission": "212.1696364",
    "continent": "Middle East",
    "year": "2009.5",
    "peryearrang": "273"
  },
  {
    "emission": "219.2725455",
    "continent": "Middle East",
    "year": "2010.5",
    "peryearrang": "274"
  },
  {
    "emission": "227.5325651",
    "continent": "Middle East",
    "year": "2011.5",
    "peryearrang": "275"
  },
  {
    "emission": "236.9285949",
    "continent": "Middle East",
    "year": "2012.5",
    "peryearrang": "276"
  },
  {
    "emission": "243.9468199",
    "continent": "Middle East",
    "year": "2013.5",
    "peryearrang": "277"
  },
  {
    "emission": "249.1511115",
    "continent": "Middle East",
    "year": "2014.5",
    "peryearrang": "278"
  },
  {
    "emission": "246.5387956",
    "continent": "Middle East",
    "year": "2015.5",
    "peryearrang": "279"
  },
  {
    "emission": "251.2028933",
    "continent": "Middle East",
    "year": "2016.5",
    "peryearrang": "280"
  },
  {
    "emission": "251.446006",
    "continent": "Middle East",
    "year": "2017.5",
    "peryearrang": "281"
  },
  {
    "emission": "255.0721234",
    "continent": "Middle East",
    "year": "2018.5",
    "peryearrang": "282"
  },
  {
    "emission": "248.8385433",
    "continent": "Middle East",
    "year": "2019.5",
    "peryearrang": "283"
  },
  {
    "emission": "229.5982761",
    "continent": "Middle East",
    "year": "2020.5",
    "peryearrang": "284"
  },
  {
    "emission": "238.0986383",
    "continent": "Middle East",
    "year": "2021.5",
    "peryearrang": "285"
  },
  {
    "emission": "18.18373098",
    "continent": " Africa",
    "year": "1965.6",
    "peryearrang": "286"
  },
  {
    "emission": "19.70049498",
    "continent": " Africa",
    "year": "1966.6",
    "peryearrang": "287"
  },
  {
    "emission": "19.57757011",
    "continent": " Africa",
    "year": "1967.6",
    "peryearrang": "288"
  },
  {
    "emission": "20.70410113",
    "continent": " Africa",
    "year": "1968.6",
    "peryearrang": "289"
  },
  {
    "emission": "21.08281114",
    "continent": " Africa",
    "year": "1969.6",
    "peryearrang": "290"
  },
  {
    "emission": "23.06692625",
    "continent": " Africa",
    "year": "1970.6",
    "peryearrang": "291"
  },
  {
    "emission": "25.19235259",
    "continent": " Africa",
    "year": "1971.6",
    "peryearrang": "292"
  },
  {
    "emission": "27.14659034",
    "continent": " Africa",
    "year": "1972.6",
    "peryearrang": "293"
  },
  {
    "emission": "29.24031201",
    "continent": " Africa",
    "year": "1973.6",
    "peryearrang": "294"
  },
  {
    "emission": "30.20276905",
    "continent": " Africa",
    "year": "1974.6",
    "peryearrang": "295"
  },
  {
    "emission": "31.71565733",
    "continent": " Africa",
    "year": "1975.6",
    "peryearrang": "296"
  },
  {
    "emission": "34.69299454",
    "continent": " Africa",
    "year": "1976.6",
    "peryearrang": "297"
  },
  {
    "emission": "36.9640105",
    "continent": " Africa",
    "year": "1977.6",
    "peryearrang": "298"
  },
  {
    "emission": "38.8876057",
    "continent": " Africa",
    "year": "1978.6",
    "peryearrang": "299"
  },
  {
    "emission": "40.97334997",
    "continent": " Africa",
    "year": "1979.6",
    "peryearrang": "300"
  },
  {
    "emission": "43.41661722",
    "continent": " Africa",
    "year": "1980.6",
    "peryearrang": "301"
  },
  {
    "emission": "46.94212474",
    "continent": " Africa",
    "year": "1981.6",
    "peryearrang": "302"
  },
  {
    "emission": "49.12670269",
    "continent": " Africa",
    "year": "1982.6",
    "peryearrang": "303"
  },
  {
    "emission": "51.23430959",
    "continent": " Africa",
    "year": "1983.6",
    "peryearrang": "304"
  },
  {
    "emission": "52.15563413",
    "continent": " Africa",
    "year": "1984.6",
    "peryearrang": "305"
  },
  {
    "emission": "53.49836733",
    "continent": " Africa",
    "year": "1985.6",
    "peryearrang": "306"
  },
  {
    "emission": "52.50406941",
    "continent": " Africa",
    "year": "1986.6",
    "peryearrang": "307"
  },
  {
    "emission": "55.34112354",
    "continent": " Africa",
    "year": "1987.6",
    "peryearrang": "308"
  },
  {
    "emission": "57.6336274",
    "continent": " Africa",
    "year": "1988.6",
    "peryearrang": "309"
  },
  {
    "emission": "59.63219123",
    "continent": " Africa",
    "year": "1989.6",
    "peryearrang": "310"
  },
  {
    "emission": "60.5357852",
    "continent": " Africa",
    "year": "1990.6",
    "peryearrang": "311"
  },
  {
    "emission": "60.88894584",
    "continent": " Africa",
    "year": "1991.6",
    "peryearrang": "312"
  },
  {
    "emission": "62.04496214",
    "continent": " Africa",
    "year": "1992.6",
    "peryearrang": "313"
  },
  {
    "emission": "62.49684304",
    "continent": " Africa",
    "year": "1993.6",
    "peryearrang": "314"
  },
  {
    "emission": "64.69735786",
    "continent": " Africa",
    "year": "1994.6",
    "peryearrang": "315"
  },
  {
    "emission": "67.06514141",
    "continent": " Africa",
    "year": "1995.6",
    "peryearrang": "316"
  },
  {
    "emission": "68.55462966",
    "continent": " Africa",
    "year": "1996.6",
    "peryearrang": "317"
  },
  {
    "emission": "70.55005003",
    "continent": " Africa",
    "year": "1997.6",
    "peryearrang": "318"
  },
  {
    "emission": "72.15320114",
    "continent": " Africa",
    "year": "1998.6",
    "peryearrang": "319"
  },
  {
    "emission": "74.87500376",
    "continent": " Africa",
    "year": "1999.6",
    "peryearrang": "320"
  },
  {
    "emission": "75.11954871",
    "continent": " Africa",
    "year": "2000.6",
    "peryearrang": "321"
  },
  {
    "emission": "75.71092714",
    "continent": " Africa",
    "year": "2001.6",
    "peryearrang": "322"
  },
  {
    "emission": "78.1821399",
    "continent": " Africa",
    "year": "2002.6",
    "peryearrang": "323"
  },
  {
    "emission": "80.48711315",
    "continent": " Africa",
    "year": "2003.6",
    "peryearrang": "324"
  },
  {
    "emission": "83.89697114",
    "continent": " Africa",
    "year": "2004.6",
    "peryearrang": "325"
  },
  {
    "emission": "87.55627485",
    "continent": " Africa",
    "year": "2005.6",
    "peryearrang": "326"
  },
  {
    "emission": "88.52881582",
    "continent": " Africa",
    "year": "2006.6",
    "peryearrang": "327"
  },
  {
    "emission": "91.67642266",
    "continent": " Africa",
    "year": "2007.6",
    "peryearrang": "328"
  },
  {
    "emission": "96.34498674",
    "continent": " Africa",
    "year": "2008.6",
    "peryearrang": "329"
  },
  {
    "emission": "99.56654179",
    "continent": " Africa",
    "year": "2009.6",
    "peryearrang": "330"
  },
  {
    "emission": "103.753677",
    "continent": " Africa",
    "year": "2010.6",
    "peryearrang": "331"
  },
  {
    "emission": "101.9440006",
    "continent": " Africa",
    "year": "2011.6",
    "peryearrang": "332"
  },
  {
    "emission": "107.9182992",
    "continent": " Africa",
    "year": "2012.6",
    "peryearrang": "333"
  },
  {
    "emission": "111.8816375",
    "continent": " Africa",
    "year": "2013.6",
    "peryearrang": "334"
  },
  {
    "emission": "113.0045784",
    "continent": " Africa",
    "year": "2014.6",
    "peryearrang": "335"
  },
  {
    "emission": "115.8551796",
    "continent": " Africa",
    "year": "2015.6",
    "peryearrang": "336"
  },
  {
    "emission": "116.3513057",
    "continent": " Africa",
    "year": "2016.6",
    "peryearrang": "337"
  },
  {
    "emission": "117.3799316",
    "continent": " Africa",
    "year": "2017.6",
    "peryearrang": "338"
  },
  {
    "emission": "118.451713",
    "continent": " Africa",
    "year": "2018.6",
    "peryearrang": "339"
  },
  {
    "emission": "118.6354709",
    "continent": " Africa",
    "year": "2019.6",
    "peryearrang": "340"
  },
  {
    "emission": "105.3541321",
    "continent": " Africa",
    "year": "2020.6",
    "peryearrang": "341"
  },
  {
    "emission": "114.3874442",
    "continent": " Africa",
    "year": "2021.6",
    "peryearrang": "342"
  },
  {
    "emission": "105.1551686",
    "continent": "Asia Pacific",
    "year": "1965.7",
    "peryearrang": "343"
  },
  {
    "emission": "119.7801104",
    "continent": "Asia Pacific",
    "year": "1966.7",
    "peryearrang": "344"
  },
  {
    "emission": "139.7729814",
    "continent": "Asia Pacific",
    "year": "1967.7",
    "peryearrang": "345"
  },
  {
    "emission": "159.7712643",
    "continent": "Asia Pacific",
    "year": "1968.7",
    "peryearrang": "346"
  },
  {
    "emission": "185.646781",
    "continent": "Asia Pacific",
    "year": "1969.7",
    "peryearrang": "347"
  },
  {
    "emission": "215.5127972",
    "continent": "Asia Pacific",
    "year": "1970.7",
    "peryearrang": "348"
  },
  {
    "emission": "239.3098685",
    "continent": "Asia Pacific",
    "year": "1971.7",
    "peryearrang": "349"
  },
  {
    "emission": "257.75684",
    "continent": "Asia Pacific",
    "year": "1972.7",
    "peryearrang": "350"
  },
  {
    "emission": "292.9417558",
    "continent": "Asia Pacific",
    "year": "1973.7",
    "peryearrang": "351"
  },
  {
    "emission": "290.7923274",
    "continent": "Asia Pacific",
    "year": "1974.7",
    "peryearrang": "352"
  },
  {
    "emission": "288.549008",
    "continent": "Asia Pacific",
    "year": "1975.7",
    "peryearrang": "353"
  },
  {
    "emission": "306.9307793",
    "continent": "Asia Pacific",
    "year": "1976.7",
    "peryearrang": "354"
  },
  {
    "emission": "322.5918812",
    "continent": "Asia Pacific",
    "year": "1977.7",
    "peryearrang": "355"
  },
  {
    "emission": "340.3304946",
    "continent": "Asia Pacific",
    "year": "1978.7",
    "peryearrang": "356"
  },
  {
    "emission": "348.3122843",
    "continent": "Asia Pacific",
    "year": "1979.7",
    "peryearrang": "357"
  },
  {
    "emission": "328.0557328",
    "continent": "Asia Pacific",
    "year": "1980.7",
    "peryearrang": "358"
  },
  {
    "emission": "318.1649527",
    "continent": "Asia Pacific",
    "year": "1981.7",
    "peryearrang": "359"
  },
  {
    "emission": "308.9883152",
    "continent": "Asia Pacific",
    "year": "1982.7",
    "peryearrang": "360"
  },
  {
    "emission": "310.8090402",
    "continent": "Asia Pacific",
    "year": "1983.7",
    "peryearrang": "361"
  },
  {
    "emission": "322.0373238",
    "continent": "Asia Pacific",
    "year": "1984.7",
    "peryearrang": "362"
  },
  {
    "emission": "318.4751588",
    "continent": "Asia Pacific",
    "year": "1985.7",
    "peryearrang": "363"
  },
  {
    "emission": "329.2959776",
    "continent": "Asia Pacific",
    "year": "1986.7",
    "peryearrang": "364"
  },
  {
    "emission": "339.8036543",
    "continent": "Asia Pacific",
    "year": "1987.7",
    "peryearrang": "365"
  },
  {
    "emission": "369.3162129",
    "continent": "Asia Pacific",
    "year": "1988.7",
    "peryearrang": "366"
  },
  {
    "emission": "392.0131685",
    "continent": "Asia Pacific",
    "year": "1989.7",
    "peryearrang": "367"
  },
  {
    "emission": "415.4219455",
    "continent": "Asia Pacific",
    "year": "1990.7",
    "peryearrang": "368"
  },
  {
    "emission": "432.4851015",
    "continent": "Asia Pacific",
    "year": "1991.7",
    "peryearrang": "369"
  },
  {
    "emission": "461.9326039",
    "continent": "Asia Pacific",
    "year": "1992.7",
    "peryearrang": "370"
  },
  {
    "emission": "480.9983469",
    "continent": "Asia Pacific",
    "year": "1993.7",
    "peryearrang": "371"
  },
  {
    "emission": "508.7657085",
    "continent": "Asia Pacific",
    "year": "1994.7",
    "peryearrang": "372"
  },
  {
    "emission": "546.6919172",
    "continent": "Asia Pacific",
    "year": "1995.7",
    "peryearrang": "373"
  },
  {
    "emission": "574.5034302",
    "continent": "Asia Pacific",
    "year": "1996.7",
    "peryearrang": "374"
  },
  {
    "emission": "602.5246485",
    "continent": "Asia Pacific",
    "year": "1997.7",
    "peryearrang": "375"
  },
  {
    "emission": "588.6690349",
    "continent": "Asia Pacific",
    "year": "1998.7",
    "peryearrang": "376"
  },
  {
    "emission": "613.436659",
    "continent": "Asia Pacific",
    "year": "1999.7",
    "peryearrang": "377"
  },
  {
    "emission": "631.8991821",
    "continent": "Asia Pacific",
    "year": "2000.7",
    "peryearrang": "378"
  },
  {
    "emission": "636.2311131",
    "continent": "Asia Pacific",
    "year": "2001.7",
    "peryearrang": "379"
  },
  {
    "emission": "652.6021252",
    "continent": "Asia Pacific",
    "year": "2002.7",
    "peryearrang": "380"
  },
  {
    "emission": "680.0082037",
    "continent": "Asia Pacific",
    "year": "2003.7",
    "peryearrang": "381"
  },
  {
    "emission": "720.8404741",
    "continent": "Asia Pacific",
    "year": "2004.7",
    "peryearrang": "382"
  },
  {
    "emission": "723.804781",
    "continent": "Asia Pacific",
    "year": "2005.7",
    "peryearrang": "383"
  },
  {
    "emission": "739.4373901",
    "continent": "Asia Pacific",
    "year": "2006.7",
    "peryearrang": "384"
  },
  {
    "emission": "763.5704639",
    "continent": "Asia Pacific",
    "year": "2007.7",
    "peryearrang": "385"
  },
  {
    "emission": "762.7488703",
    "continent": "Asia Pacific",
    "year": "2008.7",
    "peryearrang": "386"
  },
  {
    "emission": "768.3218824",
    "continent": "Asia Pacific",
    "year": "2009.7",
    "peryearrang": "387"
  },
  {
    "emission": "820.4741681",
    "continent": "Asia Pacific",
    "year": "2010.7",
    "peryearrang": "388"
  },
  {
    "emission": "841.237629",
    "continent": "Asia Pacific",
    "year": "2011.7",
    "peryearrang": "389"
  },
  {
    "emission": "879.2926974",
    "continent": "Asia Pacific",
    "year": "2012.7",
    "peryearrang": "390"
  },
  {
    "emission": "891.4665946",
    "continent": "Asia Pacific",
    "year": "2013.7",
    "peryearrang": "391"
  },
  {
    "emission": "905.1305991",
    "continent": "Asia Pacific",
    "year": "2014.7",
    "peryearrang": "392"
  },
  {
    "emission": "945.6471713",
    "continent": "Asia Pacific",
    "year": "2015.7",
    "peryearrang": "393"
  },
  {
    "emission": "982.1020453",
    "continent": "Asia Pacific",
    "year": "2016.7",
    "peryearrang": "394"
  },
  {
    "emission": "1012.398543",
    "continent": "Asia Pacific",
    "year": "2017.7",
    "peryearrang": "395"
  },
  {
    "emission": "1035.519991",
    "continent": "Asia Pacific",
    "year": "2018.7",
    "peryearrang": "396"
  },
  {
    "emission": "1053.461663",
    "continent": "Asia Pacific",
    "year": "2019.7",
    "peryearrang": "397"
  },
  {
    "emission": "997.9446334",
    "continent": "Asia Pacific",
    "year": "2020.7",
    "peryearrang": "398"
  },
  {
    "emission": "1041.646481",
    "continent": "Asia Pacific",
    "year": "2021.7",
    "peryearrang": "399"
  }
]

